autodiff/__init__.py
autodiff/ad.py
autodiff/reverse.py
autodiff/rootfinding.py
autodiff/vector_forward.py
autodiff/vector_reverse.py
autodiff_AsiaUnionCS107-0.0.15.dist-info/LICENSE
autodiff_AsiaUnionCS107-0.0.15.dist-info/METADATA
autodiff_AsiaUnionCS107-0.0.15.dist-info/WHEEL
autodiff_AsiaUnionCS107-0.0.15.dist-info/top_level.txt
autodiff_AsiaUnionCS107-0.0.15.dist-info/RECORD
