Metadata-Version: 2.1
Name: autodiff-AsiaUnionCS107
Version: 0.0.15
Summary: An Automatic Differentiation Package
Home-page: https://github.com/AsiaUnionCS107/cs107-FinalProject
Author: AsiaUnionCS107
License: UNKNOWN
Platform: UNKNOWN
Classifier: Programming Language :: Python :: 3
Classifier: License :: OSI Approved :: MIT License
Classifier: Operating System :: OS Independent
Requires-Python: >=3.6
